simple_templates/__init__.py
simple_templates/apps.py
simple_templates/middleware.py
simple_templates/tests.py
simple_templates/utils.py
simple_templates/templatetags/__init__.py
simple_templates/templatetags/simple_templates.py
django_simple_templates-1.0.0.dist-info/LICENSE
django_simple_templates-1.0.0.dist-info/METADATA
django_simple_templates-1.0.0.dist-info/WHEEL
django_simple_templates-1.0.0.dist-info/top_level.txt
django_simple_templates-1.0.0.dist-info/RECORD
