Metadata-Version: 2.2
Name: django-simple-templates
Version: 1.0.0
Summary: Easy, designer-friendly templates and A/B testing friendly tools for Django.
Author-email: James Addison <addi00@gmail.com>
Maintainer-email: James Addison <addi00@gmail.com>
License: MIT
Project-URL: Homepage, https://github.com/jaddison/django-simple-templates
Project-URL: Documentation, https://github.com/jaddison/django-simple-templates
Project-URL: Issues, https://github.com/jaddison/django-simple-templates/issues
Keywords: a/b testing,split testing,a/b,split
Classifier: Development Status :: 5 - Production/Stable
Classifier: Intended Audience :: Developers
Classifier: Environment :: Web Environment
Classifier: Operating System :: OS Independent
Classifier: Programming Language :: Python
Classifier: Framework :: Django
Classifier: Topic :: Internet :: WWW/HTTP :: WSGI
Requires-Python: >=3.8
License-File: LICENSE
Requires-Dist: django>=4.2
